odoo/addons/shopinvader_product_seasonality/README.rst
odoo/addons/shopinvader_product_seasonality/__init__.py
odoo/addons/shopinvader_product_seasonality/__manifest__.py
odoo/addons/shopinvader_product_seasonality/components/__init__.py
odoo/addons/shopinvader_product_seasonality/components/seasonal_config_line_event_listener.py
odoo/addons/shopinvader_product_seasonality/data/ir_export_product_seasonality.xml
odoo/addons/shopinvader_product_seasonality/data/queue_job_channel_data.xml
odoo/addons/shopinvader_product_seasonality/data/queue_job_function_data.xml
odoo/addons/shopinvader_product_seasonality/i18n/shopinvader_product_seasonality.pot
odoo/addons/shopinvader_product_seasonality/models/__init__.py
odoo/addons/shopinvader_product_seasonality/models/seasonal_config_line.py
odoo/addons/shopinvader_product_seasonality/models/shopinvader_backend.py
odoo/addons/shopinvader_product_seasonality/models/shopinvader_seasonal_config_line.py
odoo/addons/shopinvader_product_seasonality/readme/CONTRIBUTORS.rst
odoo/addons/shopinvader_product_seasonality/readme/DESCRIPTION.rst
odoo/addons/shopinvader_product_seasonality/security/ir.model.access.csv
odoo/addons/shopinvader_product_seasonality/services/__init__.py
odoo/addons/shopinvader_product_seasonality/services/customer.py
odoo/addons/shopinvader_product_seasonality/static/description/index.html
odoo/addons/shopinvader_product_seasonality/tests/__init__.py
odoo/addons/shopinvader_product_seasonality/tests/test_customer.py
odoo/addons/shopinvader_product_seasonality/tests/test_prod_seasonality.py
odoo/addons/shopinvader_product_seasonality/views/seasonal_config_line.xml
odoo/addons/shopinvader_product_seasonality/views/shopinvader_backend.xml
odoo/addons/shopinvader_product_seasonality/views/shopinvader_seasonal_config.xml
odoo14_addon_shopinvader_product_seasonality-14.0.1.0.1.dist-info/METADATA
odoo14_addon_shopinvader_product_seasonality-14.0.1.0.1.dist-info/WHEEL
odoo14_addon_shopinvader_product_seasonality-14.0.1.0.1.dist-info/top_level.txt
odoo14_addon_shopinvader_product_seasonality-14.0.1.0.1.dist-info/RECORD
